simu/__init__.py
simu/random.py
simu-0.0.1.dist-info/LICENSE
simu-0.0.1.dist-info/METADATA
simu-0.0.1.dist-info/WHEEL
simu-0.0.1.dist-info/top_level.txt
simu-0.0.1.dist-info/RECORD
