Metadata-Version: 2.1
Name: simu
Version: 0.0.1
Summary: a simulation data generator
Home-page: https://github.com/uncle-lv/simu
Author: uncle-lv
Author-email: uncle.lv@outlook.com
License: UNKNOWN
Project-URL: Bug Reports, https://github.com/uncle-lv/simu/issues
Project-URL: Source, https://github.com/uncle-lv/simu
Keywords: mock,test,random
Platform: UNKNOWN
Requires-Python: >=3.7
License-File: LICENSE
